{"_id":"1623946f-1aae-4e28-9ad6-fb3e386bf72d","code":"male","label":"Male","links":{"code_list":{"id":"crime-sex","href":"http://localhost:22400/code-lists/crime-sex"},"self":{"id":"male","href":"http://localhost:22400/code-lists/crime-sex/codes/male"}}}
{"_id":"db9cf851-4c2d-4ed0-8481-b66e5e3e79b9","code":"female","label":"Female","links":{"code_list":{"id":"crime-sex","href":"http://localhost:22400/code-lists/crime-sex"},"self":{"id":"female","href":"http://localhost:22400/code-lists/crime-sex/codes/female"}}}
{"_id":"9cf66fe2-d353-4e5d-ae7b-97896312b6e5","code":"all-adults","label":"All adults","links":{"code_list":{"id":"crime-sex","href":"http://localhost:22400/code-lists/crime-sex"},"self":{"id":"all-adults","href":"http://localhost:22400/code-lists/crime-sex/codes/all-adults"}}}
