{"_id":"056df332-fc6e-4f74-a2ff-d24a7ccd4712","code":"2","label":"Female","links":{"code_list":{"id":"midyearpopsex","href":"http://localhost:22400/code-lists/midyearpopsex"},"self":{"id":"2","href":"http://localhost:22400/code-lists/midyearpopsex/codes/2"}}}
{"_id":"0521b54b-5821-4b2b-a13d-77467ece56ed","code":"1","label":"Male","links":{"code_list":{"id":"midyearpopsex","href":"http://localhost:22400/code-lists/midyearpopsex"},"self":{"id":"1","href":"http://localhost:22400/code-lists/midyearpopsex/codes/1"}}}
{"_id":"67feb1c0-7301-41b5-a53e-f5b991e70905","code":"0","label":"All","links":{"code_list":{"id":"midyearpopsex","href":"http://localhost:22400/code-lists/midyearpopsex"},"self":{"id":"0","href":"http://localhost:22400/code-lists/midyearpopsex/codes/0"}}}
{"_id":"b35aebc9-6dfe-4175-b72b-c486a3bbffd6","code":"2","label":"Female","links":{"code_list":{"id":"midyearpopsex","href":"http://localhost:22400/code-lists/midyearpopsex"},"self":{"id":"2","href":"http://localhost:22400/code-lists/midyearpopsex/codes/2"}}}
{"_id":"aeaaa93a-5502-493f-8039-aadf9503ad71","code":"1","label":"Male","links":{"code_list":{"id":"midyearpopsex","href":"http://localhost:22400/code-lists/midyearpopsex"},"self":{"id":"1","href":"http://localhost:22400/code-lists/midyearpopsex/codes/1"}}}
{"_id":"20fd0c63-e7eb-41d7-83b3-377cfdbbb415","code":"0","label":"All","links":{"code_list":{"id":"midyearpopsex","href":"http://localhost:22400/code-lists/midyearpopsex"},"self":{"id":"0","href":"http://localhost:22400/code-lists/midyearpopsex/codes/0"}}}
